spantom/__init__.py
spantom/dashboard.py
spantom/spantom.py
spantom-1.0.0.dist-info/licenses/LICENSE
spantom-1.0.0.dist-info/METADATA
spantom-1.0.0.dist-info/WHEEL
spantom-1.0.0.dist-info/entry_points.txt
spantom-1.0.0.dist-info/top_level.txt
spantom-1.0.0.dist-info/RECORD
