Metadata-Version: 2.4
Name: spantom
Version: 1.0.0
Summary: A lightweight tracing library for Python
Home-page: https://github.com/rowland-208/spantom
Author: James Rowland
Author-email: rowland.208@gmail.com
Project-URL: Bug Tracker, https://github.com/rowland-208/spantom/issues
Classifier: License :: OSI Approved :: MIT License
Classifier: Operating System :: OS Independent
Classifier: Programming Language :: Python
Classifier: Programming Language :: Python :: 3
Requires-Python: >=3.7
License-File: LICENSE
Provides-Extra: dashboard
Requires-Dist: matplotlib; extra == "dashboard"
Requires-Dist: click; extra == "dashboard"
Requires-Dist: dash; extra == "dashboard"
Requires-Dist: dash-bootstrap-components; extra == "dashboard"
Requires-Dist: pandas; extra == "dashboard"
Requires-Dist: plotly; extra == "dashboard"
Dynamic: license-file
